fkinter.py
fkinter-0.0.1.dist-info/WHEEL
fkinter-0.0.1.dist-info/METADATA
fkinter-0.0.1.dist-info/RECORD
