Metadata-Version: 2.1
Name: fkinter
Version: 0.0.1
Summary: Figma to Tkinter generator! 1.0.0!
Author: ozodbeksobirjonovich
Requires-Python: >=3.7,<4.0
Classifier: Programming Language :: Python :: 3
Classifier: Programming Language :: Python :: 3.7
Classifier: Programming Language :: Python :: 3.8
Classifier: Programming Language :: Python :: 3.9
Classifier: Programming Language :: Python :: 3.10
Classifier: Programming Language :: Python :: 3.11
Requires-Dist: colorama (>=0.4.6,<0.5.0)
Requires-Dist: tkdesigner (>=1.0.6,<2.0.0)
